HxongResourceDownloader/DirCleaner.py
HxongResourceDownloader/ResourceCheck.py
HxongResourceDownloader/TgDownloader.py
HxongResourceDownloader/__init__.py
HxongResourceDownloader/__main__.py
HxongResourceDownloader/setting.py
HxongResourceDownloader-0.0.3.dist-info/LICENSE
HxongResourceDownloader-0.0.3.dist-info/METADATA
HxongResourceDownloader-0.0.3.dist-info/WHEEL
HxongResourceDownloader-0.0.3.dist-info/top_level.txt
HxongResourceDownloader-0.0.3.dist-info/RECORD
